{
  "generated": "2026-06-29T05:22:52.060657Z",
  "period": {
    "start": "2025-06-29",
    "end": "2026-06-29"
  },
  "total": 653,
  "total_unique": 0,
  "hits_by_day": [
    {
      "date": "2026-05-09",
      "count": 21
    },
    {
      "date": "2026-05-10",
      "count": 43
    },
    {
      "date": "2026-05-11",
      "count": 18
    },
    {
      "date": "2026-05-12",
      "count": 7
    },
    {
      "date": "2026-05-13",
      "count": 10
    },
    {
      "date": "2026-05-14",
      "count": 4
    },
    {
      "date": "2026-05-15",
      "count": 31
    },
    {
      "date": "2026-05-16",
      "count": 14
    },
    {
      "date": "2026-05-17",
      "count": 4
    },
    {
      "date": "2026-05-18",
      "count": 1
    },
    {
      "date": "2026-05-19",
      "count": 3
    },
    {
      "date": "2026-05-20",
      "count": 11
    },
    {
      "date": "2026-05-21",
      "count": 21
    },
    {
      "date": "2026-05-22",
      "count": 26
    },
    {
      "date": "2026-05-23",
      "count": 8
    },
    {
      "date": "2026-05-24",
      "count": 9
    },
    {
      "date": "2026-05-25",
      "count": 10
    },
    {
      "date": "2026-05-26",
      "count": 3
    },
    {
      "date": "2026-05-27",
      "count": 10
    },
    {
      "date": "2026-05-28",
      "count": 6
    },
    {
      "date": "2026-05-29",
      "count": 11
    },
    {
      "date": "2026-05-30",
      "count": 2
    },
    {
      "date": "2026-05-31",
      "count": 15
    },
    {
      "date": "2026-06-01",
      "count": 13
    },
    {
      "date": "2026-06-02",
      "count": 23
    },
    {
      "date": "2026-06-03",
      "count": 50
    },
    {
      "date": "2026-06-04",
      "count": 18
    },
    {
      "date": "2026-06-05",
      "count": 23
    },
    {
      "date": "2026-06-06",
      "count": 2
    },
    {
      "date": "2026-06-07",
      "count": 10
    },
    {
      "date": "2026-06-08",
      "count": 8
    },
    {
      "date": "2026-06-09",
      "count": 12
    },
    {
      "date": "2026-06-10",
      "count": 29
    },
    {
      "date": "2026-06-11",
      "count": 8
    },
    {
      "date": "2026-06-12",
      "count": 8
    },
    {
      "date": "2026-06-13",
      "count": 4
    },
    {
      "date": "2026-06-14",
      "count": 11
    },
    {
      "date": "2026-06-15",
      "count": 21
    },
    {
      "date": "2026-06-16",
      "count": 9
    },
    {
      "date": "2026-06-17",
      "count": 4
    },
    {
      "date": "2026-06-18",
      "count": 6
    },
    {
      "date": "2026-06-19",
      "count": 6
    },
    {
      "date": "2026-06-20",
      "count": 5
    },
    {
      "date": "2026-06-21",
      "count": 6
    },
    {
      "date": "2026-06-22",
      "count": 13
    },
    {
      "date": "2026-06-23",
      "count": 19
    },
    {
      "date": "2026-06-24",
      "count": 18
    },
    {
      "date": "2026-06-25",
      "count": 9
    },
    {
      "date": "2026-06-26",
      "count": 4
    },
    {
      "date": "2026-06-27",
      "count": 8
    },
    {
      "date": "2026-06-28",
      "count": 15
    },
    {
      "date": "2026-06-29",
      "count": 3
    }
  ],
  "hits": [
    {
      "path": "/",
      "count": 184
    },
    {
      "path": "/galeria",
      "count": 62
    },
    {
      "path": "/serveis",
      "count": 43
    },
    {
      "path": "/festivals",
      "count": 33
    },
    {
      "path": "/blog",
      "count": 28
    },
    {
      "path": "/noticies",
      "count": 27
    },
    {
      "path": "/contacte",
      "count": 25
    },
    {
      "path": "/qui-som",
      "count": 16
    },
    {
      "path": "/obra",
      "count": 11
    },
    {
      "path": "/cerca",
      "count": 9
    },
    {
      "path": "/ca",
      "count": 9
    },
    {
      "path": "/festivals/calella-harmonica-festival",
      "count": 8
    },
    {
      "path": "/serveis-fotografics-2/books-per-actors-i-actrius",
      "count": 8
    },
    {
      "path": "/noticies/guia-exposicions-espais-fotografics-barcelona",
      "count": 7
    },
    {
      "path": "/serveis/books-per-actors",
      "count": 7
    },
    {
      "path": "/festivals/nou-barris-meets-new-orleans",
      "count": 7
    },
    {
      "path": "/legal/privacitat",
      "count": 5
    },
    {
      "path": "/serveis/books-artistics",
      "count": 5
    },
    {
      "path": "/es/servicios-fotograficos/books-para-actores-y-actrices",
      "count": 5
    },
    {
      "path": "/festivals/carnestoltes-nou-barris",
      "count": 5
    },
    {
      "path": "/en/noticies/photo-exhibitions-spaces-barcelona-guide",
      "count": 4
    },
    {
      "path": "/noticies/2026-06-la-juganera",
      "count": 4
    },
    {
      "path": "/contacte/politica-de-ptivacitat-avis-legal",
      "count": 4
    },
    {
      "path": "/festivals/im-jazz",
      "count": 4
    },
    {
      "path": "/en",
      "count": 4
    },
    {
      "path": "/en/content/photography-studio",
      "count": 4
    },
    {
      "path": "/sessio-amb-la-ballarina-nahomi-itzel",
      "count": 4
    },
    {
      "path": "/es/caffenol-una-tecnica-de-revelado-alternativa",
      "count": 4
    },
    {
      "path": "/festivals/flamenco-de-barrio",
      "count": 4
    },
    {
      "path": "/en/lomography-great-photos-simple-camera",
      "count": 3
    },
    {
      "path": "/serveis/concerts",
      "count": 3
    },
    {
      "path": "/festivals/vijazz",
      "count": 3
    },
    {
      "path": "/festivals/festival-blues-barcelona",
      "count": 3
    },
    {
      "path": "/on-veure-exposicions-de-fotografia-a-barcelona",
      "count": 3
    },
    {
      "path": "/es/guia-completa-de-exposiciones-y-espacios-fotograficos-en-barcelona",
      "count": 3
    },
    {
      "path": "/en/comprehensive-guide-to-photography-exhibitions-and-spaces-in-barcelona",
      "count": 3
    },
    {
      "path": "/ca/contacte",
      "count": 3
    },
    {
      "path": "/ca/galeria",
      "count": 3
    },
    {
      "path": "/en/testing-adox-hr-50-film",
      "count": 2
    },
    {
      "path": "/en/from-chance-to-creativity-a-photo-shoot-with-an-oriental-dress",
      "count": 2
    },
    {
      "path": "/en/testing-vintage-cameras",
      "count": 2
    },
    {
      "path": "/en/bran-new-calendar-of-9-barris-acull",
      "count": 2
    },
    {
      "path": "/serveis/sessio-banda",
      "count": 2
    },
    {
      "path": "/serveis/portada-disc",
      "count": 2
    },
    {
      "path": "/serveis/edicions-limitades",
      "count": 2
    },
    {
      "path": "/serveis/portada-identitat",
      "count": 2
    },
    {
      "path": "/serveis/teatre-dansa",
      "count": 2
    },
    {
      "path": "/serveis/festivals-i-sales",
      "count": 2
    },
    {
      "path": "/serveis/fotollibre",
      "count": 2
    },
    {
      "path": "/en/serveis",
      "count": 2
    }
  ],
  "by_lang": {
    "ca": 25,
    "es": 23,
    "en": 49
  },
  "by_section": {
    "inici": 197,
    "galeria": 67,
    "serveis": 74,
    "festivals": 79,
    "blog": 32,
    "noticies": 45,
    "contacte": 34,
    "qui-som": 19,
    "obra": 14,
    "cerca": 11,
    "serveis-fotografics-2": 10,
    "legal": 5,
    "servicios-fotograficos": 5,
    "content": 4,
    "sessio-amb-la-ballarina-nahomi-itzel": 4,
    "caffenol-una-tecnica-de-revelado-alternativa": 4,
    "lomography-great-photos-simple-camera": 3,
    "on-veure-exposicions-de-fotografia-a-barcelona": 3,
    "guia-completa-de-exposiciones-y-espacios-fotograficos-en-barcelona": 3,
    "comprehensive-guide-to-photography-exhibitions-and-spaces-in-barcelona": 3,
    "testing-adox-hr-50-film": 2,
    "from-chance-to-creativity-a-photo-shoot-with-an-oriental-dress": 2,
    "testing-vintage-cameras": 2,
    "bran-new-calendar-of-9-barris-acull": 2,
    "moviendo-las-imagenes-fijas": 2,
    "photography-services": 2,
    "dr-roland-f-beers-paper-devoloper-revelador-para-papel-fotografico-de-altas-prestaciones": 2,
    "practicas-de-revelado-de-placas-de-8x10": 2,
    "revelado-de-pelicula-color-con-proceso-de-blanco-y-negro": 2,
    "probando-la-pelicula-adox-hr-50": 2,
    "vijazz-2025-the-jazz-that-brought-me-back-home": 1,
    "wp-content": 1,
    "photographic-services": 1,
    "gypsy-wedding-bon-pastor-barcelona": 1,
    "photos-of-musical-groups": 1,
    "example-of-a-session-with-traditional-photography": 1,
    "cambo-sc-first-test": 1,
    "provant-la-pelicula-kono-monolit-iso64": 1,
    "a-different-perspective-analog-photography-with-personality-and-mystery": 1,
    "guia-completa-de-exposiciones-y-espacios-fotograficos-en-barcelona%60": 1,
    "flamenco-i-baixa-velocitat-3": 1,
    "forced-tests-sample-photographs": 1,
    "tag": 2,
    "de-la-casualitat-a-la-creativitat-una-sessio-fotografica-amb-vestit-oriental": 1,
    "retrats-per-comencar-lany-amb-bona-cara-i-millor-portfolio": 1,
    "sessio-amb-eli": 1
  },
  "noticies_top": [
    {
      "path": "/noticies/guia-exposicions-espais-fotografics-barcelona",
      "count": 7
    },
    {
      "path": "/en/noticies/photo-exhibitions-spaces-barcelona-guide",
      "count": 4
    },
    {
      "path": "/noticies/2026-06-la-juganera",
      "count": 4
    }
  ],
  "festivals_top": [
    {
      "path": "/festivals/calella-harmonica-festival",
      "count": 8
    },
    {
      "path": "/festivals/nou-barris-meets-new-orleans",
      "count": 7
    },
    {
      "path": "/festivals/carnestoltes-nou-barris",
      "count": 5
    },
    {
      "path": "/festivals/im-jazz",
      "count": 4
    },
    {
      "path": "/festivals/flamenco-de-barrio",
      "count": 4
    },
    {
      "path": "/festivals/vijazz",
      "count": 3
    },
    {
      "path": "/festivals/festival-blues-barcelona",
      "count": 3
    }
  ],
  "wizard_funnel": {
    "wizard-s1": 12,
    "wizard-s2": 15,
    "wizard-s3": 5,
    "wizard-s4": 4,
    "wizard-sent": 3
  },
  "browsers": [
    {
      "name": "Chrome",
      "id": "Chrome",
      "count": 384
    },
    {
      "name": "Safari",
      "id": "Safari",
      "count": 311
    },
    {
      "name": "Desconegut",
      "id": "Desconegut",
      "count": 20
    },
    {
      "name": "Firefox",
      "id": "Firefox",
      "count": 19
    }
  ],
  "systems": [
    {
      "name": "macOS",
      "id": "macOS",
      "count": 443
    },
    {
      "name": "iOS",
      "id": "iOS",
      "count": 89
    },
    {
      "name": "Windows",
      "id": "Windows",
      "count": 84
    },
    {
      "name": "Android",
      "id": "Android",
      "count": 67
    },
    {
      "name": "Linux",
      "id": "Linux",
      "count": 47
    },
    {
      "name": "Chrome OS",
      "id": "Chrome OS",
      "count": 4
    }
  ],
  "sizes": [
    {
      "name": "desktop",
      "id": "desktop",
      "count": 301
    },
    {
      "name": "desktophd",
      "id": "desktophd",
      "count": 217
    },
    {
      "name": "phone",
      "id": "phone",
      "count": 144
    },
    {
      "name": "tablet",
      "id": "tablet",
      "count": 72
    }
  ],
  "locations": [
    {
      "name": "Spain",
      "id": "ES",
      "count": 623
    },
    {
      "name": "United States",
      "id": "US",
      "count": 45
    },
    {
      "name": "Germany",
      "id": "DE",
      "count": 6
    },
    {
      "name": "Indonesia",
      "id": "ID",
      "count": 6
    },
    {
      "name": "Sweden",
      "id": "SE",
      "count": 6
    },
    {
      "name": "Malaysia",
      "id": "MY",
      "count": 4
    },
    {
      "name": "Argentina",
      "id": "AR",
      "count": 3
    },
    {
      "name": "Switzerland",
      "id": "CH",
      "count": 3
    },
    {
      "name": "Netherlands",
      "id": "NL",
      "count": 3
    },
    {
      "name": "Russia",
      "id": "RU",
      "count": 3
    },
    {
      "name": "Singapore",
      "id": "SG",
      "count": 3
    },
    {
      "name": "United Arab Emirates",
      "id": "AE",
      "count": 2
    },
    {
      "name": "France",
      "id": "FR",
      "count": 2
    },
    {
      "name": "United Kingdom",
      "id": "GB",
      "count": 2
    },
    {
      "name": "New Zealand",
      "id": "NZ",
      "count": 2
    }
  ],
  "refs": [
    {
      "name": "Desconegut",
      "id": "Desconegut",
      "count": 165
    },
    {
      "name": "Google",
      "id": "Google",
      "count": 62
    },
    {
      "name": "blog.pocallum.cat",
      "id": "blog.pocallum.cat",
      "count": 6
    },
    {
      "name": "pocallum-cat.translate.goog",
      "id": "pocallum-cat.translate.goog",
      "count": 5
    },
    {
      "name": "www.facebook.com",
      "id": "www.facebook.com",
      "count": 4
    },
    {
      "name": "bing.com",
      "id": "bing.com",
      "count": 3
    },
    {
      "name": "Yandex",
      "id": "Yandex",
      "count": 3
    },
    {
      "name": "about.pocallum.cat",
      "id": "about.pocallum.cat",
      "count": 3
    },
    {
      "name": "ig",
      "id": "ig",
      "count": 2
    },
    {
      "name": "www.bing.com",
      "id": "www.bing.com",
      "count": 2
    }
  ]
}